pyety/__init__.py
pyety/ddb_parser.py
pyety-0.0.3.dist-info/LICENSE
pyety-0.0.3.dist-info/METADATA
pyety-0.0.3.dist-info/WHEEL
pyety-0.0.3.dist-info/top_level.txt
pyety-0.0.3.dist-info/RECORD
