Metadata-Version: 2.1
Name: pyety
Version: 0.0.3
Summary: DynamoDB experimentation.
Home-page: https://github.com/thorwhalen/newut/tree/master/pyety
Author: Thor Whalen
License: mit
Platform: any
License-File: LICENSE
